ashar/__init__.py
ashar/asharversion.py
ashar-1.1.8.dist-info/LICENSE
ashar-1.1.8.dist-info/METADATA
ashar-1.1.8.dist-info/WHEEL
ashar-1.1.8.dist-info/top_level.txt
ashar-1.1.8.dist-info/RECORD
